gdelt2py/__init__.py
gdelt2py/check.py
gdelt2py/gdelt2.py
gdelt2py/gdelt2event.py
gdelt2py/task.py
gdelt2py-0.1.6.dist-info/LICENSE
gdelt2py-0.1.6.dist-info/METADATA
gdelt2py-0.1.6.dist-info/WHEEL
gdelt2py-0.1.6.dist-info/top_level.txt
gdelt2py-0.1.6.dist-info/RECORD
