Metadata-Version: 2.1
Name: gdelt2py
Version: 0.1.6
Summary: A Python package for downloading and processing Gdelt data (current only GKG, will be extened)
Author-email: RakerZh <gitrustz10@gmail.com>
License: MIT License
Project-URL: Homepage, https://github.com/RakerZh/gdelt2py
Project-URL: Bug Tracker, https://github.com/RakerZh/gdelt2py/issues
Classifier: Programming Language :: Python :: 3.7
Classifier: Programming Language :: Python :: 3.8
Classifier: Programming Language :: Python :: 3.9
Classifier: Programming Language :: Python :: 3.10
Classifier: Programming Language :: Python :: 3.11
Classifier: License :: OSI Approved :: MIT License
Classifier: Operating System :: OS Independent
Requires-Python: >=3.7
License-File: LICENSE
Requires-Dist: aiohttp (>=3.8.3)
Requires-Dist: numpy (>=1.24.2)
Requires-Dist: pandas (>=1.5.2)
